LICENSE
README.md
setup.py
ColorateStart/__init__.py
ColorateStart.egg-info/PKG-INFO
ColorateStart.egg-info/SOURCES.txt
ColorateStart.egg-info/dependency_links.txt
ColorateStart.egg-info/top_level.txt