Metadata-Version: 2.1
Name: ColorateStart
Version: 1.0
Summary: Another Library
Home-page: https://github.com/InvalidAccount69/ColorateStart
Author: Rainbow_Rain
Author-email: 
License: Apache License 2.0
Platform: UNKNOWN
License-File: LICENSE
